{
  "0": "\u0000",
  "1": "\u0001",
  "2": "\u0002",
  "3": "\u0003",
  "4": "\u009c",
  "5": "\t",
  "6": "\u0086",
  "7": "\u007f",
  "8": "\u0097",
  "9": "\u008d",
  "10": "\u008e",
  "11": "\u000b",
  "12": "\f",
  "13": "\r",
  "14": "\u000e",
  "15": "\u000f",
  "16": "\u0010",
  "17": "\u0011",
  "18": "\u0012",
  "19": "\u0013",
  "20": "\u009d",
  "21": "\u0085",
  "22": "\b",
  "23": "\u0087",
  "24": "\u0018",
  "25": "\u0019",
  "26": "\u0092",
  "27": "\u008f",
  "28": "\u001c",
  "29": "\u001d",
  "30": "\u001e",
  "31": "\u001f",
  "32": "\u0080",
  "33": "\u0081",
  "34": "\u0082",
  "35": "\u0083",
  "36": "\u0084",
  "37": "\n",
  "38": "\u0017",
  "39": "\u001b",
  "40": "\u0088",
  "41": "\u0089",
  "42": "\u008a",
  "43": "\u008b",
  "44": "\u008c",
  "45": "\u0005",
  "46": "\u0006",
  "47": "\u0007",
  "48": "\u0090",
  "49": "\u0091",
  "50": "\u0016",
  "51": "\u0093",
  "52": "\u0094",
  "53": "\u0095",
  "54": "\u0096",
  "55": "\u0004",
  "56": "\u0098",
  "57": "\u0099",
  "58": "\u009a",
  "59": "\u009b",
  "60": "\u0014",
  "61": "\u0015",
  "62": "\u009e",
  "63": "\u001a",
  "64": " ",
  "65": "\u0391",
  "66": "\u0392",
  "67": "\u0393",
  "68": "\u0394",
  "69": "\u0395",
  "70": "\u0396",
  "71": "\u0397",
  "72": "\u0398",
  "73": "\u0399",
  "74": "[",
  "75": ".",
  "76": "<",
  "77": "(",
  "78": "+",
  "79": "!",
  "80": "&",
  "81": "\u039a",
  "82": "\u039b",
  "83": "\u039c",
  "84": "\u039d",
  "85": "\u039e",
  "86": "\u039f",
  "87": "\u03a0",
  "88": "\u03a1",
  "89": "\u03a3",
  "90": "]",
  "91": "$",
  "92": "*",
  "93": ")",
  "94": ";",
  "95": "^",
  "96": "-",
  "97": "/",
  "98": "\u03a4",
  "99": "\u03a5",
  "100": "\u03a6",
  "101": "\u03a7",
  "102": "\u03a8",
  "103": "\u03a9",
  "104": "\u03aa",
  "105": "\u03ab",
  "106": "|",
  "107": ",",
  "108": "%",
  "109": "_",
  "110": ">",
  "111": "?",
  "112": "\u00a8",
  "113": "\u0386",
  "114": "\u0388",
  "115": "\u0389",
  "116": "\u00a0",
  "117": "\u038a",
  "118": "\u038c",
  "119": "\u038e",
  "120": "\u038f",
  "121": "`",
  "122": ":",
  "123": "#",
  "124": "@",
  "125": "'",
  "126": "=",
  "127": "\"",
  "128": "\u0385",
  "129": "a",
  "130": "b",
  "131": "c",
  "132": "d",
  "133": "e",
  "134": "f",
  "135": "g",
  "136": "h",
  "137": "i",
  "138": "\u03b1",
  "139": "\u03b2",
  "140": "\u03b3",
  "141": "\u03b4",
  "142": "\u03b5",
  "143": "\u03b6",
  "144": "\u00b0",
  "145": "j",
  "146": "k",
  "147": "l",
  "148": "m",
  "149": "n",
  "150": "o",
  "151": "p",
  "152": "q",
  "153": "r",
  "154": "\u03b7",
  "155": "\u03b8",
  "156": "\u03b9",
  "157": "\u03ba",
  "158": "\u03bb",
  "159": "\u03bc",
  "160": "\u00b4",
  "161": "~",
  "162": "s",
  "163": "t",
  "164": "u",
  "165": "v",
  "166": "w",
  "167": "x",
  "168": "y",
  "169": "z",
  "170": "\u03bd",
  "171": "\u03be",
  "172": "\u03bf",
  "173": "\u03c0",
  "174": "\u03c1",
  "175": "\u03c3",
  "176": "\u00a3",
  "177": "\u03ac",
  "178": "\u03ad",
  "179": "\u03ae",
  "180": "\u03ca",
  "181": "\u03af",
  "182": "\u03cc",
  "183": "\u03cd",
  "184": "\u03cb",
  "185": "\u03ce",
  "186": "\u03c2",
  "187": "\u03c4",
  "188": "\u03c5",
  "189": "\u03c6",
  "190": "\u03c7",
  "191": "\u03c8",
  "192": "{",
  "193": "A",
  "194": "B",
  "195": "C",
  "196": "D",
  "197": "E",
  "198": "F",
  "199": "G",
  "200": "H",
  "201": "I",
  "202": "\u00ad",
  "203": "\u03c9",
  "204": "\u0390",
  "205": "\u03b0",
  "206": "\u2018",
  "207": "\u2015",
  "208": "}",
  "209": "J",
  "210": "K",
  "211": "L",
  "212": "M",
  "213": "N",
  "214": "O",
  "215": "P",
  "216": "Q",
  "217": "R",
  "218": "\u00b1",
  "219": "\u00bd",
  "220": "?",
  "221": "\u0387",
  "222": "\u2019",
  "223": "\u00a6",
  "224": "\\",
  "225": "?",
  "226": "S",
  "227": "T",
  "228": "U",
  "229": "V",
  "230": "W",
  "231": "X",
  "232": "Y",
  "233": "Z",
  "234": "\u00b2",
  "235": "\u00a7",
  "236": "?",
  "237": "?",
  "238": "\u00ab",
  "239": "\u00ac",
  "240": "0",
  "241": "1",
  "242": "2",
  "243": "3",
  "244": "4",
  "245": "5",
  "246": "6",
  "247": "7",
  "248": "8",
  "249": "9",
  "250": "\u00b3",
  "251": "\u00a9",
  "252": "?",
  "253": "?",
  "254": "\u00bb",
  "255": "\u009f"
}
